mlpproc/__init__.py
mlpproc/__main__.py
mlpproc/blocks.py
mlpproc/commands.py
mlpproc/conditions.py
mlpproc/context.py
mlpproc/defaults.py
mlpproc/defs.py
mlpproc/errors.py
mlpproc/final_actions.py
mlpproc/labels.py
mlpproc/preprocessor.py
mlpproc-1.0.3.data/data/LICENSE
mlpproc-1.0.3.data/scripts/mlpp
mlpproc-1.0.3.dist-info/LICENSE
mlpproc-1.0.3.dist-info/METADATA
mlpproc-1.0.3.dist-info/WHEEL
mlpproc-1.0.3.dist-info/top_level.txt
mlpproc-1.0.3.dist-info/RECORD
